LICENSE
MANIFEST.in
README.md
mymodule.cp313-win_amd64.pyd
setup.py
matkhau.egg-info/PKG-INFO
matkhau.egg-info/SOURCES.txt
matkhau.egg-info/dependency_links.txt
matkhau.egg-info/top_level.txt