Metadata-Version: 2.1
Name: matkhau
Version: 0.1.0
Summary: A package with a compiled extension
Home-page: https://github.com/yourusername/your_project
Author: Your Name
Author-email: your_email@example.com
Classifier: Programming Language :: Python :: 3
Classifier: Operating System :: OS Independent
License-File: LICENSE
